pandadoc/__init__.py
pandadoc/_version.py
pandadoc/core.py
pandadoc/exceptions.py
pandadoc-0.1.0.dist-info/LICENSE
pandadoc-0.1.0.dist-info/METADATA
pandadoc-0.1.0.dist-info/WHEEL
pandadoc-0.1.0.dist-info/top_level.txt
pandadoc-0.1.0.dist-info/RECORD
