Metadata-Version: 2.1
Name: pandadoc
Version: 0.1.0
Summary: pandadoc: lightweight pandoc wrapper
Home-page: https://github.com/chris-mcdo/pandadoc
Author: Christopher McDonald
Author-email: cmcdonal33@gmail.com
License: MIT
Project-URL: Source, https://github.com/chris-mcdo/pandadoc
Project-URL: Tracker, https://github.com/chris-mcdo/pandadoc/issues
Keywords: pandoc,pandocfilters,markdown,latex
Platform: win32
Platform: linux
Platform: osx
Classifier: Development Status :: 4 - Beta
Classifier: Intended Audience :: Developers
Classifier: License :: OSI Approved :: MIT License
Classifier: Operating System :: MacOS :: MacOS X
Classifier: Operating System :: Microsoft :: Windows
Classifier: Operating System :: POSIX
Classifier: Programming Language :: Python :: 3
Classifier: Programming Language :: Python :: 3 :: Only
Classifier: Programming Language :: Python :: 3.8
Classifier: Programming Language :: Python :: 3.9
Classifier: Programming Language :: Python :: 3.10
Classifier: Topic :: Text Processing
Classifier: Topic :: Text Processing :: Filters
Requires-Python: >=3.8
License-File: LICENSE
